{
  "components": {
    "schemas": {
      "RepoStorage": {
        "type": "object",
        "properties": {
          "id": {
            "type": "integer"
          },
          "type": {
            "type": "string"
          },
          "name": {
            "type": "string"
          },
          "clusters": {
            "type": "array",
            "items": {
              "type": "object",
              "properties": {
                "id": {
                  "type": "integer"
                },
                "name": {
                  "type": "string"
                }
              }
            }
          }
        },
        "nullable": true,
        "additionalProperties": false
      }
    }
  }
}
